dimentyy/btp/__init__.py
dimentyy_better_telethon_parser-0.1.dev8.dist-info/METADATA
dimentyy_better_telethon_parser-0.1.dev8.dist-info/WHEEL
dimentyy_better_telethon_parser-0.1.dev8.dist-info/licenses/LICENSE.md
dimentyy_better_telethon_parser-0.1.dev8.dist-info/RECORD
