Metadata-Version: 2.3
Name: dimentyy.better-telethon-parser
Version: 0.1.dev8
Summary: Better Telethon parser — use all Telegram formatting features.
Project-URL: Author, https://t.me/dimentyy
Author: dimentyy
License-File: LICENSE.md
Classifier: License :: OSI Approved :: MIT License
Requires-Dist: telethon
